bouillabaisse/__init__.py
bouillabaisse/recettes.py
bouillabaisse-0.0.2.dist-info/LICENSE
bouillabaisse-0.0.2.dist-info/METADATA
bouillabaisse-0.0.2.dist-info/WHEEL
bouillabaisse-0.0.2.dist-info/top_level.txt
bouillabaisse-0.0.2.dist-info/RECORD
