Metadata-Version: 2.1
Name: bouillabaisse
Version: 0.0.2
Summary: recettes de bouillabaisse
Home-page: https://github.com/flotpython/bidule
Author: Alex Grumberg
Author-email: ag@gmail.com
License: Creative Commons BY-CC-ND 4.0
Platform: UNKNOWN
